MANIFEST.in
README.rst
VERSION
setup.py
hitchnode/__init__.py
hitchnode/node_package.py
hitchnode/node_service.py
hitchnode/static_serve.py
hitchnode.egg-info/PKG-INFO
hitchnode.egg-info/SOURCES.txt
hitchnode.egg-info/dependency_links.txt
hitchnode.egg-info/not-zip-safe
hitchnode.egg-info/requires.txt
hitchnode.egg-info/top_level.txt