Metadata-Version: 1.1
Name: hitchnode
Version: 0.3.2
Summary: Hitch plug-in to run node.js applications.
Home-page: https://hitchtest.readthedocs.org/en/latest/plugins/hitchnode.html
Author: Colm O'Connor
Author-email: colm.oconnor.github@gmail.com
License: AGPL
Keywords: hitch testing framework bdd tdd declarative tests testing service command line nodejs node
Platform: UNKNOWN
Classifier: Development Status :: 3 - Alpha
Classifier: Intended Audience :: Developers
Classifier: License :: OSI Approved :: GNU Affero General Public License v3 or later (AGPLv3+)
Classifier: Topic :: Software Development :: Quality Assurance
Classifier: Topic :: Software Development :: Testing
Classifier: Topic :: Software Development :: Libraries
Classifier: Topic :: Utilities
Classifier: Environment :: Console
Classifier: Operating System :: Unix
Classifier: Programming Language :: Python :: 3
Classifier: Programming Language :: Python :: 3.3
Classifier: Programming Language :: Python :: 3.4
